grainpy/__init__.py
grainpy/classify.py
grainpy/grainsize.py
grainpy/util.py
grainpy-0.1.0.dist-info/LICENSE
grainpy-0.1.0.dist-info/METADATA
grainpy-0.1.0.dist-info/WHEEL
grainpy-0.1.0.dist-info/top_level.txt
grainpy-0.1.0.dist-info/RECORD
