Metadata-Version: 2.1
Name: grainpy
Version: 0.1.0
Summary: Python package for compiling, analyzing, visualizing, and interpreting grain size distribution data.
Home-page: https://github.com/masseygeo/GrainPy
Author: Matt Massey
Author-email: mamass1@g.uky.edu
License: UNKNOWN
Project-URL: Bug Tracker, https://github.com/masseygeo/GrainPy/issues
Platform: UNKNOWN
Classifier: Programming Language :: Python :: 3
Classifier: License :: OSI Approved :: GNU General Public License v3 (GPLv3)
Classifier: Operating System :: OS Independent
Requires-Python: >=3.6
License-File: LICENSE
Requires-Dist: pandas
Requires-Dist: numpy
Requires-Dist: matplotlib
Requires-Dist: scipy
Requires-Dist: openpyxl
